bbox_overlay/__init__.py
bbox_overlay/__main__.py
bbox_overlay/cli.py
bbox_overlay/overlay.py
bbox_overlay-0.1.3.dist-info/licenses/LICENSE
bbox_overlay-0.1.3.dist-info/METADATA
bbox_overlay-0.1.3.dist-info/WHEEL
bbox_overlay-0.1.3.dist-info/entry_points.txt
bbox_overlay-0.1.3.dist-info/top_level.txt
bbox_overlay-0.1.3.dist-info/RECORD
