Metadata-Version: 2.4
Name: bbox-overlay
Version: 0.1.3
Summary: Simple screen overlay for drawing bounding boxes
Home-page: https://github.com/albertoburgosplaza/bbox-overlay
Author-email: Alberto Burgos Plaza <albertoburgosplaza@gmail.com>
License: MIT
Project-URL: Homepage, https://github.com/albertoburgosplaza/bbox-overlay
Project-URL: Documentation, https://github.com/albertoburgosplaza/bbox-overlay#readme
Project-URL: Issues, https://github.com/albertoburgosplaza/bbox-overlay/issues
Project-URL: Changelog, https://github.com/albertoburgosplaza/bbox-overlay/blob/main/CHANGELOG.md
Project-URL: Source, https://github.com/albertoburgosplaza/bbox-overlay
Project-URL: CI, https://github.com/albertoburgosplaza/bbox-overlay/actions/workflows/ci.yml
Keywords: bbox,overlay,x11,tkinter
Classifier: Development Status :: 3 - Alpha
Classifier: Environment :: X11 Applications
Classifier: Intended Audience :: Developers
Classifier: License :: OSI Approved :: MIT License
Classifier: Operating System :: POSIX :: Linux
Classifier: Programming Language :: Python :: 3
Classifier: Programming Language :: Python :: 3 :: Only
Classifier: Programming Language :: Python :: 3.8
Classifier: Programming Language :: Python :: 3.9
Classifier: Programming Language :: Python :: 3.10
Classifier: Programming Language :: Python :: 3.11
Classifier: Programming Language :: Python :: 3.12
Classifier: Topic :: Multimedia :: Graphics
Classifier: Topic :: Utilities
Requires-Python: >=3.8
License-File: LICENSE
Provides-Extra: dev
Requires-Dist: mypy>=1.8.0; extra == "dev"
Requires-Dist: pytest>=7.4.0; extra == "dev"
Requires-Dist: ruff>=0.4.0; extra == "dev"
Dynamic: license-file
